{
    "type": "FeatureCollection", 
    "features": [
        {
            "geometry": {
                "type": "Point", 
                "coordinates": [
                    4.8287408, 
                    45.7766432
                ]
            }, 
            "type": "Feature", 
            "properties": {
                "originURL": "https://scontent-cdt1-1.cdninstagram.com/vp/a6a81e85a4a950828cddf3ae5bcc679d/5C9C5F76/t51.2885-15/e35/44252091_2134415613282921_2244742160533882030_n.jpg", 
                "originally_localized": true, 
                "author": "epices_fonds_de_placards", 
                "instagramid": "1908192695111593048", 
                "timestamp": 1541694317, 
                "imageURL": "https://scontent-cdt1-1.cdninstagram.com/vp/60e30c9c83d6edf91a7a12f7ae153d13/5CAC44EE/t51.2885-15/sh0.08/e35/c0.135.1080.1080/s640x640/44252091_2134415613282921_2244742160533882030_n.jpg", 
                "mustbepublished": true, 
                "insta_infos": {
                    "author": "epices_fonds_de_placards", 
                    "timestamp": 1541694317, 
                    "imageURL": "https://scontent-cdt1-1.cdninstagram.com/vp/a6a81e85a4a950828cddf3ae5bcc679d/5C9C5F76/t51.2885-15/e35/44252091_2134415613282921_2244742160533882030_n.jpg", 
                    "authorid": "2876693898", 
                    "location": {
                        "id": "216569581", 
                        "slug": "la-croix-rousse-rhone-alpes-france", 
                        "address_json": "{\"street_address\": \"\", \"zip_code\": \"\", \"city_name\": \"La Croix Rousse, Rhone-Alpes, France\", \"region_name\": \"\", \"country_code\": \"FR\", \"exact_city_match\": true, \"exact_region_match\": false, \"exact_country_match\": false}", 
                        "name": "La Croix Rousse, Rhone-Alpes, France", 
                        "has_public_page": true
                    }, 
                    "id": "1908192695111593048"
                }, 
                "caption": "Aujourd'hui sur le blog, l'histoire de la Porteuse d'\u00c2mes de @cap_phi\nD\u00e8s que je l'ai vue, j'ai su ce qu'elle vivait \ud83d\ude0d\nLien dans ma bio pour conna\u00eetre son histoire et merci @cap_phi \ud83d\udc4c\nCr\u00e9dit @graphull_____ pour la photo\n#instaphoto #instapicture #streetart #urbanart #artderue #globalstreetart #igersstreetart #ilovestreetart #onlylyon #mylyon #frenchstreetart #streetartlyon #streetarteverywhere #worldart #streetartoftheday #globalstreetart #streetartlyon #murals #muralsdaily #streetartchat  #collage #pasteup #amazone #capphi #monster #histoire #fiction", 
                "authorid": "2876693898", 
                "editURL": "http://geojson.io/#id=github:streetartcapphi/locations/blob/master/input/contrib/2018-11-08/1908192695111593048_2876693898.json", 
                "instagramcode": "Bp7QyVrHyxY", 
                "post_date": "2018-11-08 17:25:17", 
                "validated": false
            }
        }
    ]
}