{
    "type": "FeatureCollection", 
    "features": [
        {
            "geometry": {
                "type": "Point", 
                "coordinates": [
                    4.8186741, 
                    45.7266101
                ]
            }, 
            "type": "Feature", 
            "properties": {
                "post_date": "2018-12-12 14:56:44", 
                "originally_localized": false, 
                "author": "cap_phi", 
                "editURL": "http://geojson.io/#id=github:streetartcapphi/locations/blob/master/input/capphi/instagram/2018-12-12/1932788072049674794.geojson", 
                "imageURL": "https://scontent-cdt1-1.cdninstagram.com/vp/5f002278db38b46447e37633fbaeb4b8/5C131FDC/t51.2885-15/e15/47468570_2053620504724918_1737731598227552832_n.jpg", 
                "mustbepublished": true, 
                "originURL": "https://scontent-cdt1-1.cdninstagram.com/vp/5f002278db38b46447e37633fbaeb4b8/5C131FDC/t51.2885-15/e15/47468570_2053620504724918_1737731598227552832_n.jpg", 
                "caption": "#wip #skate #skull #lyongerland #capphi #board", 
                "validated": false, 
                "id": "1932788072049674794"
            }
        }, 
        {
            "geometry": {
                "type": "Point", 
                "coordinates": [
                    4.8186741, 
                    45.7266101
                ]
            }, 
            "type": "Feature", 
            "properties": {
                "originURL": "https://scontent-cdt1-1.cdninstagram.com/vp/fe71405abf990b42cb5873a7335006a8/5CB0686A/t51.2885-15/e35/46105378_133334020995023_1517971458994392237_n.jpg?_nc_ht=scontent-cdt1-1.cdninstagram.com", 
                "originally_localized": true, 
                "author": "garzaf69", 
                "instagramid": "1931139439566709578", 
                "timestamp": 1544429782, 
                "imageURL": "https://scontent-cdt1-1.cdninstagram.com/vp/16a4f553464c65c75d190a992f2649bc/5CA6A58F/t51.2885-15/sh0.08/e35/s640x640/46105378_133334020995023_1517971458994392237_n.jpg?_nc_ht=scontent-cdt1-1.cdninstagram.com", 
                "mustbepublished": true, 
                "insta_infos": {
                    "author": "garzaf69", 
                    "timestamp": 1544429782, 
                    "imageURL": "https://scontent-cdt1-1.cdninstagram.com/vp/fe71405abf990b42cb5873a7335006a8/5CB0686A/t51.2885-15/e35/46105378_133334020995023_1517971458994392237_n.jpg?_nc_ht=scontent-cdt1-1.cdninstagram.com", 
                    "authorid": "810473762", 
                    "location": null, 
                    "id": "1931139439566709578"
                }, 
                "caption": "By @cap_phi 4/6 #capphi  #map_phi #monstres #streetcollages #pochoir #collage #streetart #streetartist #streetartlyon #streearteverywhere #lyon #pentesdelacroixrousse #croixrousse #onlylyon  #urban #urbanart #urbanartist #graffiti #graff #graffitilyon #tag #streetcollages #collage #igerslyon #igers", 
                "authorid": "810473762", 
                "editURL": "http://geojson.io/#id=github:streetartcapphi/locations/blob/master/input/contrib/2018-12-10/1931139439566709578_810473762.json", 
                "instagramcode": "BrMyRazHuNK", 
                "post_date": "2018-12-10 09:16:22", 
                "validated": false
            }
        }
    ]
}