{
    "type": "FeatureCollection", 
    "features": [
        {
            "geometry": {
                "type": "Point", 
                "coordinates": [
                    4.8186741, 
                    45.7266101
                ]
            }, 
            "type": "Feature", 
            "properties": {
                "originURL": "https://scontent-cdt1-1.cdninstagram.com/vp/d2bcd9d9d317d6740856baeee25adb08/5C8DC6EA/t51.2885-15/fr/e15/s1080x1080/41203427_697488980612875_8670335658204367991_n.jpg", 
                "originally_localized": true, 
                "author": "streetartpostal", 
                "instagramid": "1866238429189927986", 
                "timestamp": 1536692978, 
                "imageURL": "https://scontent-cdt1-1.cdninstagram.com/vp/a9e71b1de7c9e699b7a047b3520e4c1d/5C9DCDC5/t51.2885-15/e15/c77.0.925.925/s640x640/41203427_697488980612875_8670335658204367991_n.jpg", 
                "mustbepublished": true, 
                "insta_infos": {
                    "author": "streetartpostal", 
                    "timestamp": 1536692978, 
                    "imageURL": "https://scontent-cdt1-1.cdninstagram.com/vp/d2bcd9d9d317d6740856baeee25adb08/5C8DC6EA/t51.2885-15/fr/e15/s1080x1080/41203427_697488980612875_8670335658204367991_n.jpg", 
                    "authorid": "6179926796", 
                    "location": null, 
                    "id": "1866238429189927986"
                }, 
                "caption": "#artistaurbano171 #capphi #ttone", 
                "authorid": "6179926796", 
                "editURL": "http://geojson.io/#id=github:streetartcapphi/locations/blob/master/input/contrib/2018-09-11/1866238429189927986_6179926796.json", 
                "instagramcode": "BnmNfauDHQy", 
                "post_date": "2018-09-11 21:09:38", 
                "validated": false
            }
        }, 
        {
            "geometry": {
                "type": "Point", 
                "coordinates": [
                    4.8320114, 
                    45.7578137
                ]
            }, 
            "type": "Feature", 
            "properties": {
                "originURL": "https://scontent-cdt1-1.cdninstagram.com/vp/cda901d471990e4eed689713bf7f0049/5C9B434A/t51.2885-15/e35/41283665_671557109893863_4434753751422785708_n.jpg", 
                "originally_localized": true, 
                "author": "91shots", 
                "instagramid": "1865482564748865893", 
                "timestamp": 1536602872, 
                "imageURL": "https://scontent-cdt1-1.cdninstagram.com/vp/cdada42760bf3c9e01c41708ca1c272b/5C968BAF/t51.2885-15/sh0.08/e35/s640x640/41283665_671557109893863_4434753751422785708_n.jpg", 
                "mustbepublished": true, 
                "insta_infos": {
                    "author": "91shots", 
                    "timestamp": 1536602872, 
                    "imageURL": "https://scontent-cdt1-1.cdninstagram.com/vp/cda901d471990e4eed689713bf7f0049/5C9B434A/t51.2885-15/e35/41283665_671557109893863_4434753751422785708_n.jpg", 
                    "authorid": "1732572522", 
                    "location": {
                        "id": "213168722", 
                        "slug": "lyon-france", 
                        "address_json": "{\"street_address\": \"\", \"zip_code\": \"\", \"city_name\": \"Lyon, France\", \"region_name\": \"\", \"country_code\": \"FR\", \"exact_city_match\": true, \"exact_region_match\": false, \"exact_country_match\": false}", 
                        "name": "Lyon, France", 
                        "has_public_page": true
                    }, 
                    "id": "1865482564748865893"
                }, 
                "caption": "art by: @cap_phi\n\n#capphi #lyon #onlylyon #streetartLyon #pasteup #lyonstreetart #wild #animals #streetartlyonnais #streetculture #Lyongraffiti #graffitiLyonnais #contraculturaurbana #urbanstyle #streetshots #91shots", 
                "authorid": "1732572522", 
                "editURL": "http://geojson.io/#id=github:streetartcapphi/locations/blob/master/input/contrib/2018-09-10/1865482564748865893_1732572522.json", 
                "instagramcode": "BnjhoJGinFl", 
                "post_date": "2018-09-10 20:07:52", 
                "validated": false
            }
        }
    ]
}