{
    "type": "FeatureCollection", 
    "features": [
        {
            "geometry": {
                "type": "Point", 
                "coordinates": [
                    4.8186741, 
                    45.7266101
                ]
            }, 
            "type": "Feature", 
            "properties": {
                "originURL": "https://scontent-cdt1-1.cdninstagram.com/vp/eb2b9a395470e9897957c6d0b1b305ac/5C1023E1/t51.2885-15/e35/37645781_1068520079975678_5536637183017877504_n.jpg", 
                "originally_localized": true, 
                "author": "fellassari", 
                "instagramid": "1836971556121476376", 
                "timestamp": 1533204095, 
                "imageURL": "https://scontent-cdt1-1.cdninstagram.com/vp/890c35c6508d99ef1d36cb494442161b/5C119D5B/t51.2885-15/sh0.08/e35/s640x640/37645781_1068520079975678_5536637183017877504_n.jpg", 
                "mustbepublished": true, 
                "insta_infos": {
                    "author": "fellassari", 
                    "timestamp": 1533204095, 
                    "imageURL": "https://scontent-cdt1-1.cdninstagram.com/vp/eb2b9a395470e9897957c6d0b1b305ac/5C1023E1/t51.2885-15/e35/37645781_1068520079975678_5536637183017877504_n.jpg", 
                    "authorid": "6832502255", 
                    "location": {
                        "slug": "lyon-7e", 
                        "has_public_page": true, 
                        "name": "Lyon 7e", 
                        "id": "481880730"
                    }, 
                    "id": "1836971556121476376"
                }, 
                "caption": "rue S\u00e9bastien Gryphe #streetart #streetartlyon #capphi #zorm #ruesebastiengryphe", 
                "authorid": "6832502255", 
                "editURL": "http://geojson.io/#id=github:streetartcapphi/locations/blob/master/input/contrib/2018-08-02/1836971556121476376_6832502255.json", 
                "instagramcode": "Bl-O-XJHf0Y", 
                "post_date": "2018-08-02 12:01:35", 
                "validated": false
            }
        }, 
        {
            "geometry": {
                "type": "Point", 
                "coordinates": [
                    4.8186741, 
                    45.7266101
                ]
            }, 
            "type": "Feature", 
            "properties": {
                "originURL": "https://scontent-cdg2-1.cdninstagram.com/vp/52a45c9a47ca27532ea4e012f266a486/5BD04AA5/t51.2885-15/e35/36790988_224051745111495_3419070469020581888_n.jpg", 
                "originally_localized": true, 
                "author": "fellassari", 
                "instagramid": "1831876564042444672", 
                "timestamp": 1532596725, 
                "imageURL": "https://scontent-cdg2-1.cdninstagram.com/vp/7f748bde776f2ed7f9a55b89bfbffa36/5BF45A40/t51.2885-15/sh0.08/e35/s640x640/36790988_224051745111495_3419070469020581888_n.jpg", 
                "mustbepublished": true, 
                "insta_infos": {
                    "author": "fellassari", 
                    "timestamp": 1532596725, 
                    "imageURL": "https://scontent-cdg2-1.cdninstagram.com/vp/52a45c9a47ca27532ea4e012f266a486/5BD04AA5/t51.2885-15/e35/36790988_224051745111495_3419070469020581888_n.jpg", 
                    "authorid": "6832502255", 
                    "location": {
                        "slug": "lyon-2eme", 
                        "has_public_page": true, 
                        "name": "Lyon 2\u00e8me", 
                        "id": "397421663"
                    }, 
                    "id": "1831876564042444672"
                }, 
                "caption": "Confluence #streetart #streetartlyon  #capphi", 
                "authorid": "6832502255", 
                "editURL": "http://geojson.io/#id=github:streetartcapphi/locations/blob/master/input/contrib/2018-07-26/1831876564042444672_6832502255.json", 
                "instagramcode": "BlsIgeAHO-A", 
                "post_date": "2018-07-26 11:18:45", 
                "validated": false
            }
        }
    ]
}