{
    "type": "FeatureCollection", 
    "features": [
        {
            "geometry": {
                "type": "Point", 
                "coordinates": [
                    4.817708730697633, 
                    45.72671954750316
                ]
            }, 
            "type": "Feature", 
            "properties": {
                "originURL": "https://www.instagram.com/p/BZiTW99g_gR", 
                "originally_localized": true, 
                "author": "isa_belledixon", 
                "instagramid": "1612936757794568209", 
                "timestamp": 1506497066, 
                "imageURL": "https://scontent-cdg2-1.cdninstagram.com/t51.2885-15/s640x640/sh0.08/e35/22069117_833965250106600_8113342897459298304_n.jpg", 
                "mustbepublished": true, 
                "insta_infos": {
                    "author": "isa_belledixon", 
                    "timestamp": 1506497066, 
                    "imageURL": "https://scontent-cdg2-1.cdninstagram.com/t51.2885-15/e35/22069117_833965250106600_8113342897459298304_n.jpg", 
                    "authorid": "54122886", 
                    "location": null, 
                    "id": "1612936757794568209"
                }, 
                "caption": "Deuxi\u00e8me Eden  nouvelle petite Amazone de @cap_phi rencontr\u00e9e \ud83d\udc4c\ud83d\udc4c\n#capphi #art  #artiste #streetarteverywere #streetart  #urbanart #streetartist #streetartphotography#collage #streetartlyonnais#photography #honor8 #instapic  #igersfrance #igerslyon #aura_focus_on_lyon #toplyonphoto #croixrousse #pentesdelacroixrousse #amazone #eden #serpent #arbredevie #arbre", 
                "authorid": "54122886", 
                "editURL": "http://geojson.io/#id=github:streetartcapphi/locations/blob/master/input/contrib/2017-09-27/1612936757794568209_54122886.json", 
                "instagramcode": "BZiTW99g_gR", 
                "post_date": "2017-09-27 09:24:26", 
                "validated": false
            }
        }, 
        {
            "geometry": {
                "type": "Point", 
                "coordinates": [
                    4.823942184448243, 
                    45.7237386065975
                ]
            }, 
            "type": "Feature", 
            "properties": {
                "originURL": "https://www.instagram.com/p/BZV40XVnjyd", 
                "originally_localized": true, 
                "author": "cocottecoralie", 
                "instagramid": "1609442330930986141", 
                "timestamp": 1506080498, 
                "imageURL": "https://scontent-cdg2-1.cdninstagram.com/t51.2885-15/s640x640/sh0.08/e35/21909597_1450948901655838_1048127309061554176_n.jpg", 
                "mustbepublished": true, 
                "insta_infos": {
                    "author": "cocottecoralie", 
                    "timestamp": 1506080498, 
                    "imageURL": "https://scontent-cdg2-1.cdninstagram.com/t51.2885-15/e35/21909597_1450948901655838_1048127309061554176_n.jpg", 
                    "authorid": "2000118195", 
                    "location": null, 
                    "id": "1609442330930986141"
                }, 
                "caption": "Allez courage bient\u00f4t le week-end\n.\n.\n.\n#capphi #map_phi #sortirlatedeleau #weekend #streetart #lyonstreetart #streetarteverywhere #collage #croixrousse #littlemonster #igerlyon #igerlyonstreetart #picoftheday #instaart #instadailypic #littlefish #petitpoisson", 
                "authorid": "2000118195", 
                "editURL": "http://geojson.io/#id=github:streetartcapphi/locations/blob/master/input/contrib/2017-09-22/1609442330930986141_2000118195.json", 
                "instagramcode": "BZV40XVnjyd", 
                "post_date": "2017-09-22 13:41:38", 
                "validated": false
            }
        }
    ]
}