{
    "type": "FeatureCollection", 
    "features": [
        {
            "geometry": {
                "type": "Point", 
                "coordinates": [
                    4.820616245269776, 
                    45.727109005420246
                ]
            }, 
            "type": "Feature", 
            "properties": {
                "post_date": "2017-06-16 07:23:44", 
                "originally_localized": false, 
                "author": "cap_phi", 
                "editURL": "http://geojson.io/#id=github:streetartcapphi/locations/blob/master/input/capphi/instagram/2017-06-16/1538284507088782735_29177514.geojson", 
                "imageURL": "https://scontent.cdninstagram.com/t51.2885-15/s640x640/sh0.08/e35/19120325_357491874665463_3950474042271596544_n.jpg", 
                "mustbepublished": true, 
                "originURL": "https://www.instagram.com/p/BVZFZvog4WP/", 
                "caption": "#renaissance sous la #licorne #r\u00e9apparition d'une de mes #skell", 
                "validated": false, 
                "id": "1538284507088782735_29177514"
            }
        }, 
        {
            "geometry": {
                "type": "Point", 
                "coordinates": [
                    4.818255901336671, 
                    45.72707155766162
                ]
            }, 
            "type": "Feature", 
            "properties": {
                "originURL": "https://www.instagram.com/p/BVOoM38hyyu", 
                "originally_localized": true, 
                "author": "lepelicanquisemarrait", 
                "instagramid": "1535341329545374894", 
                "timestamp": 1497246970, 
                "imageURL": "https://scontent-cdg2-1.cdninstagram.com/t51.2885-15/s640x640/sh0.08/e35/18950015_400679646993795_7116998712005492736_n.jpg", 
                "mustbepublished": true, 
                "insta_infos": {
                    "author": "lepelicanquisemarrait", 
                    "timestamp": 1497246970, 
                    "imageURL": "https://scontent-cdg2-1.cdninstagram.com/t51.2885-15/e35/18950015_400679646993795_7116998712005492736_n.jpg", 
                    "authorid": "5533275959", 
                    "location": null, 
                    "id": "1535341329545374894"
                }, 
                "caption": "#collage de @cap_phi #streetartlyon #muraldaily #graffiti #streetart #capphi #pasteup #map_phi #lyon", 
                "authorid": "5533275959", 
                "editURL": "http://geojson.io/#id=github:streetartcapphi/locations/blob/master/input/contrib/2017-06-12/1535341329545374894_5533275959.json", 
                "instagramcode": "BVOoM38hyyu", 
                "post_date": "2017-06-12 07:56:10", 
                "validated": false
            }
        }
    ]
}