{
    "type": "FeatureCollection", 
    "features": [
        {
            "geometry": {
                "type": "Point", 
                "coordinates": [
                    4.818894267082214, 
                    45.72718390086225
                ]
            }, 
            "type": "Feature", 
            "properties": {
                "originURL": "https://www.instagram.com/p/BWkUpI0lTjQ", 
                "originally_localized": true, 
                "author": "cocottecoralie", 
                "instagramid": "1559462158877931728", 
                "timestamp": 1500122397, 
                "imageURL": "https://scontent-cdg2-1.cdninstagram.com/t51.2885-15/s640x640/sh0.08/e35/19984211_1931323190483360_3384393414173786112_n.jpg", 
                "mustbepublished": true, 
                "insta_infos": {
                    "author": "cocottecoralie", 
                    "timestamp": 1500122397, 
                    "imageURL": "https://scontent-cdg2-1.cdninstagram.com/t51.2885-15/e35/19984211_1931323190483360_3384393414173786112_n.jpg", 
                    "authorid": "2000118195", 
                    "location": null, 
                    "id": "1559462158877931728"
                }, 
                "caption": "Petit monstre des pentes .\n.\n.\n.\n #capphi #map_phi #streetart #streetarteverywhere #lyonstreetart #streetartlyon #collage #petitmonstre #petitdiable #croixrousse #pentesdelacroixrousse #lyon #igerlyon #igerlyonstreetart", 
                "authorid": "2000118195", 
                "editURL": "http://geojson.io/#id=github:streetartcapphi/locations/blob/master/input/contrib/2017-07-15/1559462158877931728_2000118195.json", 
                "instagramcode": "BWkUpI0lTjQ", 
                "post_date": "2017-07-15 14:39:57", 
                "validated": false
            }
        }, 
        {
            "geometry": {
                "type": "Point", 
                "coordinates": [
                    4.81858715415001, 
                    45.72664839624417
                ]
            }, 
            "type": "Feature", 
            "properties": {
                "originURL": "https://www.instagram.com/p/BWt-SY2DVVt", 
                "originally_localized": true, 
                "author": "jaylyonphoto", 
                "instagramid": "1562178588278347117", 
                "timestamp": 1500446221, 
                "imageURL": "https://scontent-cdg2-1.cdninstagram.com/t51.2885-15/s640x640/sh0.08/e35/c0.135.1080.1080/20184905_330184554083080_2397307554712518656_n.jpg", 
                "mustbepublished": true, 
                "insta_infos": {
                    "author": "jaylyonphoto", 
                    "timestamp": 1500446221, 
                    "imageURL": "https://scontent-cdg2-1.cdninstagram.com/t51.2885-15/e35/20184905_330184554083080_2397307554712518656_n.jpg", 
                    "authorid": "3274253394", 
                    "location": null, 
                    "id": "1562178588278347117"
                }, 
                "caption": "Aujourd'hui c'est parti pour une petite s\u00e9rie en mode street art !\n\u25fe\u25fe\u25fe\u25fe\u25fe\u25fe\u25fe\u25fe\u25fe\u25fe\u25fe\u25fe\u25fe\u25fe\u25fe\n#streetart #urban #urban_streetz #graff #graffiti #tag #art #city #lyon__only #onlylyon #lyoncity #lyonphotos #focus_on_streetart #super_france #france4dreams #hello_france #monlyon #igerslyon #bloginlyon #lepetitpaum\u00e9 #le_bonbon_lyon #croixrousse #culture #painting #love_art #pics_of_lyon #oslyon #merveillesdelyon #capphi", 
                "authorid": "3274253394", 
                "editURL": "http://geojson.io/#id=github:streetartcapphi/locations/blob/master/input/contrib/2017-07-19/1562178588278347117_3274253394.json", 
                "instagramcode": "BWt-SY2DVVt", 
                "post_date": "2017-07-19 08:37:01", 
                "validated": false
            }
        }
    ]
}