{
    "type": "FeatureCollection", 
    "features": [
        {
            "geometry": {
                "type": "Point", 
                "coordinates": [
                    4.819189310073853, 
                    45.72548374959644
                ]
            }, 
            "type": "Feature", 
            "properties": {
                "post_date": "2017-09-04 16:33:12", 
                "originally_localized": false, 
                "author": "cap_phi", 
                "editURL": "http://geojson.io/#id=github:streetartcapphi/locations/blob/master/input/capphi/instagram/2017-09-04/1596543116297375485_29177514.geojson", 
                "imageURL": "https://scontent.cdninstagram.com/t51.2885-15/sh0.08/e35/p640x640/21372241_146990415892200_3820906874794934272_n.jpg", 
                "mustbepublished": true, 
                "originURL": "https://www.instagram.com/p/BYoD4FjgA79/", 
                "caption": "#sketch #nouvelle #petite #amazone", 
                "validated": false, 
                "id": "1596543116297375485_29177514"
            }
        }, 
        {
            "geometry": {
                "type": "Point", 
                "coordinates": [
                    4.819318056106568, 
                    45.726472390108924
                ]
            }, 
            "type": "Feature", 
            "properties": {
                "originURL": "https://www.instagram.com/p/BYfqTIIgSq6", 
                "originally_localized": true, 
                "author": "isa_belledixon", 
                "instagramid": "1594178825468586682", 
                "timestamp": 1504260946, 
                "imageURL": "https://scontent-cdg2-1.cdninstagram.com/t51.2885-15/s640x640/sh0.08/e35/c109.0.861.861/21227883_374225036362252_4759356073624731648_n.jpg", 
                "mustbepublished": true, 
                "insta_infos": {
                    "author": "isa_belledixon", 
                    "timestamp": 1504260946, 
                    "imageURL": "https://scontent-cdg2-1.cdninstagram.com/t51.2885-15/e35/21227883_374225036362252_4759356073624731648_n.jpg", 
                    "authorid": "54122886", 
                    "location": null, 
                    "id": "1594178825468586682"
                }, 
                "caption": "M\u00eame les montres de @cap_phi sont amoureux \ud83d\ude0d\ud83d\ude0d\ud83d\ude0d\ud83d\ude0d\n#capphi #art  #artiste #streetarteverywere #streetart  #urbanart #streetartist #streetartphotography#collage #streetartlyonnais#photography #honor8 #instapic  #igersfrance #igerslyon #aura_focus_on_lyon #toplyonphoto #croixrousse #pentesdelacroixrousse #kawaii #monster", 
                "authorid": "54122886", 
                "editURL": "http://geojson.io/#id=github:streetartcapphi/locations/blob/master/input/contrib/2017-09-01/1594178825468586682_54122886.json", 
                "instagramcode": "BYfqTIIgSq6", 
                "post_date": "2017-09-01 12:15:46", 
                "validated": false
            }
        }
    ]
}