{
    "type": "FeatureCollection", 
    "features": [
        {
            "geometry": {
                "type": "Point", 
                "coordinates": [
                    4.8307475, 
                    45.7719149
                ]
            }, 
            "type": "Feature", 
            "properties": {
                "originURL": "https://scontent-cdg2-1.cdninstagram.com/vp/be5dbe9e92e847b3d03d7625792c5147/5BE8473F/t51.2885-15/e35/36824383_644359115936564_4791785872733241344_n.jpg", 
                "originally_localized": true, 
                "author": "epices_fonds_de_placards", 
                "instagramid": "1824124997738593353", 
                "timestamp": 1531672666, 
                "imageURL": "https://scontent-cdg2-1.cdninstagram.com/vp/a8a0795ccb2b4864cd61e88ea41d8222/5BDCB8DA/t51.2885-15/sh0.08/e35/s640x640/36824383_644359115936564_4791785872733241344_n.jpg", 
                "mustbepublished": true, 
                "insta_infos": {
                    "author": "epices_fonds_de_placards", 
                    "timestamp": 1531672666, 
                    "imageURL": "https://scontent-cdg2-1.cdninstagram.com/vp/be5dbe9e92e847b3d03d7625792c5147/5BE8473F/t51.2885-15/e35/36824383_644359115936564_4791785872733241344_n.jpg", 
                    "authorid": "2876693898", 
                    "location": {
                        "slug": "pentes-de-la-croix-rousse", 
                        "has_public_page": true, 
                        "name": "Pentes de la Croix-Rousse", 
                        "id": "235077454"
                    }, 
                    "id": "1824124997738593353"
                }, 
                "caption": "Superbe collab @cap_phi et @green_vegetal_work \ud83d\ude0d\ud83d\udc4c parfaitement situ\u00e9e en plus \ud83d\udc96\n#instaphoto #instapicture #streetart #urbanart #artderue #globalstreetart #mylyonphoto #mylyon #onlylyon #igersstreetart #ilovestreetart #lyonmonamour #onlylyonphoto #streetartlyon #frenchstreetart #streetarteverywhere #streetartlyon #worldart #streetartoftheday #tv_streetart  #globalstreetart #murals #muralsdaily #streetartchat #arturbain #collage #pasteup #plantecarnivore #collaboration #capphi #greenvegetalwork", 
                "authorid": "2876693898", 
                "instagramcode": "BlQmAVUHnxJ", 
                "post_date": "2018-07-15 18:37:46", 
                "validated": true
            }
        }
    ]
}