{
    "type": "FeatureCollection", 
    "features": [
        {
            "geometry": {
                "type": "Point", 
                "coordinates": [
                    4.8186741, 
                    45.7266101
                ]
            }, 
            "type": "Feature", 
            "properties": {
                "originURL": "https://scontent-cdt1-1.cdninstagram.com/vp/fe9a2057ddd290f4d32dc310c87764ee/5CA2EAB6/t51.2885-15/e35/43914243_498195877332575_6496947082870326719_n.jpg?_nc_ht=scontent-cdt1-1.cdninstagram.com", 
                "originally_localized": true, 
                "author": "chachi.44", 
                "instagramid": "1890865134574875100", 
                "timestamp": 1539628711, 
                "imageURL": "https://scontent-cdt1-1.cdninstagram.com/vp/5d6c4bf96fd7cd0f6a13be55c898ea0d/5C91CCF5/t51.2885-15/sh0.08/e35/c0.135.1080.1080/s640x640/43914243_498195877332575_6496947082870326719_n.jpg?_nc_ht=scontent-cdt1-1.cdninstagram.com", 
                "mustbepublished": true, 
                "insta_infos": {
                    "author": "chachi.44", 
                    "timestamp": 1539628711, 
                    "imageURL": "https://scontent-cdt1-1.cdninstagram.com/vp/fe9a2057ddd290f4d32dc310c87764ee/5CA2EAB6/t51.2885-15/e35/43914243_498195877332575_6496947082870326719_n.jpg?_nc_ht=scontent-cdt1-1.cdninstagram.com", 
                    "authorid": "3694450611", 
                    "location": null, 
                    "id": "1890865134574875100"
                }, 
                "caption": "#capphi #streetart #urbanart #streetartlyon #onlylyon #streetartfrance #muralart #graffiti #graffitilyon #graffitiart  #instagraffiti #urbanwall #arturbain #collage #collageart", 
                "authorid": "3694450611", 
                "instagramcode": "Bo9s9JYgbHc", 
                "post_date": "2018-10-15 20:38:31", 
                "validated": true
            }
        }
    ]
}