{
    "type": "FeatureCollection", 
    "features": [
        {
            "geometry": {
                "type": "Point", 
                "coordinates": [
                    4.821989536285401, 
                    45.72655477602849
                ]
            }, 
            "type": "Feature", 
            "properties": {
                "post_date": "2017-06-28 07:09:36", 
                "originally_localized": false, 
                "author": "cap_phi", 
                "editURL": "http://geojson.io/#id=github:streetartcapphi/locations/blob/master/input/capphi/instagram/2017-06-28/1546974699362404776_29177514.geojson", 
                "imageURL": "https://scontent.cdninstagram.com/t51.2885-15/s640x640/sh0.08/e35/19533632_1865197790468707_3978958965458337792_n.jpg", 
                "mustbepublished": true, 
                "originURL": "https://www.instagram.com/p/BV39Ur4A0mo/", 
                "caption": "#workonprogress #nouvelle #petite #amazone #capphi #urbanartist #streetart", 
                "validated": false, 
                "id": "1546974699362404776_29177514"
            }
        }, 
        {
            "geometry": {
                "type": "Point", 
                "coordinates": [
                    4.820122718811036, 
                    45.72505683123883
                ]
            }, 
            "type": "Feature", 
            "properties": {
                "originURL": "https://www.instagram.com/p/BV3AfoYBbSy", 
                "originally_localized": true, 
                "author": "rymchamam", 
                "instagramid": "1546707170681533618", 
                "timestamp": 1498601884, 
                "imageURL": "https://scontent-cdg2-1.cdninstagram.com/t51.2885-15/e15/c235.0.610.610/19436433_143776522858421_4340441791254757376_n.jpg", 
                "mustbepublished": true, 
                "insta_infos": {
                    "author": "rymchamam", 
                    "timestamp": 1498601884, 
                    "imageURL": "https://scontent-cdg2-1.cdninstagram.com/t51.2885-15/s1080x1080/e15/fr/19436433_143776522858421_4340441791254757376_n.jpg", 
                    "authorid": "2060505865", 
                    "location": null, 
                    "id": "1546707170681533618"
                }, 
                "caption": "#streetartlyonnais #streetart #lyon #art #capphi", 
                "authorid": "2060505865", 
                "editURL": "http://geojson.io/#id=github:streetartcapphi/locations/blob/master/input/contrib/2017-06-28/1546707170681533618_2060505865.json", 
                "instagramcode": "BV3AfoYBbSy", 
                "post_date": "2017-06-28 00:18:04", 
                "validated": false
            }
        }
    ]
}