{
    "type": "FeatureCollection", 
    "features": [
        {
            "geometry": {
                "type": "Point", 
                "coordinates": [
                    4.8186741, 
                    45.7266101
                ]
            }, 
            "type": "Feature", 
            "properties": {
                "originURL": "https://www.instagram.com/p/BY_UldVFF4Y", 
                "originally_localized": true, 
                "author": "garzaf69", 
                "instagramid": "1603090527410216472", 
                "timestamp": 1505323304, 
                "imageURL": "https://scontent-cdg2-1.cdninstagram.com/t51.2885-15/s640x640/sh0.08/e35/21569201_917073115152017_958759940258791424_n.jpg", 
                "mustbepublished": true, 
                "insta_infos": {
                    "author": "garzaf69", 
                    "timestamp": 1505323304, 
                    "imageURL": "https://scontent-cdg2-1.cdninstagram.com/t51.2885-15/e35/21569201_917073115152017_958759940258791424_n.jpg", 
                    "authorid": "810473762", 
                    "location": null, 
                    "id": "1603090527410216472"
                }, 
                "caption": "By @cap_phi #capphi #map_phi #monstres #streetcollages #pochoir #collage #streetart #streetartist #streetartlyon #streearteverywhere #lyon #pentesdelacroixrousse #croixrousse #onlylyon  #urban #urbanart #urbanartist #graffiti #graff #graffitilyon #tag #streetcollages #collage", 
                "authorid": "810473762", 
                "editURL": "http://geojson.io/#id=github:streetartcapphi/locations/blob/master/input/contrib/2017-09-13/1603090527410216472_810473762.json", 
                "instagramcode": "BY_UldVFF4Y", 
                "post_date": "2017-09-13 19:21:44", 
                "validated": false
            }
        }
    ]
}