{
    "type": "FeatureCollection", 
    "features": [
        {
            "geometry": {
                "type": "Point", 
                "coordinates": [
                    4.833190441131593, 
                    45.771695207876185
                ]
            }, 
            "type": "Feature", 
            "properties": {
                "originURL": "https://www.instagram.com/p/BVOnq2RB9as", 
                "originally_localized": true, 
                "author": "lepelicanquisemarrait", 
                "instagramid": "1535338991279658668", 
                "timestamp": 1497246692, 
                "imageURL": "https://scontent-cdg2-1.cdninstagram.com/t51.2885-15/s640x640/sh0.08/e35/19120987_1917433908469429_6422892848344989696_n.jpg", 
                "mustbepublished": true, 
                "insta_infos": {
                    "author": "lepelicanquisemarrait", 
                    "timestamp": 1497246692, 
                    "imageURL": "https://scontent-cdg2-1.cdninstagram.com/t51.2885-15/e35/19120987_1917433908469429_6422892848344989696_n.jpg", 
                    "authorid": "5533275959", 
                    "location": null, 
                    "id": "1535338991279658668"
                }, 
                "caption": "Monstre \u00e0 paillettes de @cap_phi #collage #streetartlyon #muraldaily #graffiti #streetart #lyon #capphi", 
                "authorid": "5533275959", 
                "instagramcode": "BVOnq2RB9as", 
                "post_date": "2017-06-12 07:51:32", 
                "validated": true
            }
        }
    ]
}