{
    "type": "FeatureCollection", 
    "features": [
        {
            "geometry": {
                "type": "Point", 
                "coordinates": [
                    4.833340644836427, 
                    45.771743851053024
                ]
            }, 
            "type": "Feature", 
            "properties": {
                "originURL": "https://www.instagram.com/p/BVOnq2RB9as", 
                "originally_localized": true, 
                "author": "lepelicanquisemarrait", 
                "instagramid": "1535338991279658668", 
                "timestamp": 1497246692, 
                "imageURL": "https://scontent-cdg2-1.cdninstagram.com/t51.2885-15/s640x640/sh0.08/e35/19120987_1917433908469429_6422892848344989696_n.jpg", 
                "mustbepublished": true, 
                "insta_infos": {
                    "author": "lepelicanquisemarrait", 
                    "timestamp": 1497246692, 
                    "imageURL": "https://scontent-cdg2-1.cdninstagram.com/t51.2885-15/e35/19120987_1917433908469429_6422892848344989696_n.jpg", 
                    "authorid": "5533275959", 
                    "location": null, 
                    "id": "1535338991279658668"
                }, 
                "caption": "Monstre \u00e0 paillettes de @cap_phi #collage #streetartlyon #muraldaily #graffiti #streetart #lyon #capphi", 
                "authorid": "5533275959", 
                "editURL": "http://geojson.io/#id=github:streetartcapphi/locations/blob/master/input/contrib/2017-06-12/1535338991279658668_5533275959.json", 
                "instagramcode": "BVOnq2RB9as", 
                "post_date": "2017-06-12 07:51:32", 
                "validated": false
            }
        }, 
        {
            "geometry": {
                "type": "Point", 
                "coordinates": [
                    4.818255901336671, 
                    45.72707155766162
                ]
            }, 
            "type": "Feature", 
            "properties": {
                "originURL": "https://www.instagram.com/p/BVOoM38hyyu", 
                "originally_localized": true, 
                "author": "lepelicanquisemarrait", 
                "instagramid": "1535341329545374894", 
                "timestamp": 1497246970, 
                "imageURL": "https://scontent-cdg2-1.cdninstagram.com/t51.2885-15/s640x640/sh0.08/e35/18950015_400679646993795_7116998712005492736_n.jpg", 
                "mustbepublished": true, 
                "insta_infos": {
                    "author": "lepelicanquisemarrait", 
                    "timestamp": 1497246970, 
                    "imageURL": "https://scontent-cdg2-1.cdninstagram.com/t51.2885-15/e35/18950015_400679646993795_7116998712005492736_n.jpg", 
                    "authorid": "5533275959", 
                    "location": null, 
                    "id": "1535341329545374894"
                }, 
                "caption": "#collage de @cap_phi #streetartlyon #muraldaily #graffiti #streetart #capphi #pasteup #map_phi #lyon", 
                "authorid": "5533275959", 
                "editURL": "http://geojson.io/#id=github:streetartcapphi/locations/blob/master/input/contrib/2017-06-12/1535341329545374894_5533275959.json", 
                "instagramcode": "BVOoM38hyyu", 
                "post_date": "2017-06-12 07:56:10", 
                "validated": false
            }
        }
    ]
}